MANIFEST.in
README.md
setup.py
otpdoor/README.md
otpdoor/__init__.py
otpdoor/__main__.py
otpdoor/auth.py
otpdoor/cli.py
otpdoor/config.py
otpdoor/license.txt
otpdoor/resources.py
otpdoor/setup.cfg
otpdoor.egg-info/PKG-INFO
otpdoor.egg-info/SOURCES.txt
otpdoor.egg-info/dependency_links.txt
otpdoor.egg-info/not-zip-safe
otpdoor.egg-info/requires.txt
otpdoor.egg-info/top_level.txt
otpdoor/__pycache__/__init__.cpython-312.pyc
otpdoor/__pycache__/__main__.cpython-312.pyc
otpdoor/__pycache__/auth.cpython-312.pyc
otpdoor/__pycache__/cli.cpython-312.pyc
otpdoor/__pycache__/config.cpython-312.pyc
otpdoor/static/_auth_style.css
otpdoor/static/favicon.png
otpdoor/templates/check.html
otpdoor/templates/config.html
otpdoor/templates/login.html