Metadata-Version: 2.2
Name: otpdoor
Version: 0.0.22
Summary: OTPdoor is a Python library for creating and managing OTP (One-Time Password) authentication with nginx.
Home-page: https://github.com/germanespinosa/otpdoor
Author: German Espinosa
Author-email: germanespinosa@gmail.com
License: MIT
Requires-Dist: pyotp
Requires-Dist: requests
Requires-Dist: flask
Requires-Dist: cryptography
Requires-Dist: waitress
Requires-Dist: qrcode
Dynamic: author
Dynamic: author-email
Dynamic: description
Dynamic: description-content-type
Dynamic: home-page
Dynamic: license
Dynamic: requires-dist
Dynamic: summary
